{
  "top_movers": [
    {
      "symbol": "INTC",
      "sector": "Technology",
      "returns": {
        "daily": -0.5530076862179545,
        "weekly": 2.3988317247117807,
        "monthly": 91.52502741300341
      }
    },
    {
      "symbol": "AMD",
      "sector": "Technology",
      "returns": {
        "daily": -3.4127284646018663,
        "weekly": -7.072828922742913,
        "monthly": 58.880206012786694
      }
    },
    {
      "symbol": "MU.BA",
      "sector": "CEDEAR",
      "returns": {
        "daily": -4.501810168424369,
        "weekly": 2.0521446593776194,
        "monthly": 52.898185483870975
      }
    },
    {
      "symbol": "MU",
      "sector": "Technology",
      "returns": {
        "daily": -3.8641888645745803,
        "weekly": 1.523998893866807,
        "monthly": 49.268888826459815
      }
    },
    {
      "symbol": "UNH",
      "sector": "Healthcare",
      "returns": {
        "daily": 3.405787163189422,
        "weekly": 3.3387735652022688,
        "monthly": 35.544548570701615
      }
    }
  ],
  "bottom_movers": [
    {
      "symbol": "NKE",
      "sector": "Consumer Discretionary",
      "returns": {
        "daily": -0.24368766468523262,
        "weekly": 0.7607969636067358,
        "monthly": -14.74820325735572
      }
    },
    {
      "symbol": "NOW",
      "sector": "Technology",
      "returns": {
        "daily": 0.04422434148918519,
        "weekly": 0.35488488557431364,
        "monthly": -13.44811552136238
      }
    },
    {
      "symbol": "XOM",
      "sector": "Energy",
      "returns": {
        "daily": 1.599294876943258,
        "weekly": 1.10804771735038,
        "monthly": -11.257813091619829
      }
    },
    {
      "symbol": "SPOT",
      "sector": "Communication Services",
      "returns": {
        "daily": -12.427896052386188,
        "weekly": -16.177603821036435,
        "monthly": -10.45760884949971
      }
    },
    {
      "symbol": "OXY",
      "sector": "Energy",
      "returns": {
        "daily": 2.3397942061762933,
        "weekly": 2.608546404637746,
        "monthly": -9.830768291766823
      }
    }
  ],
  "sector_ranking": [
    {
      "sector": "Technology",
      "avg_return": 21.59823118422362,
      "count": 16
    },
    {
      "sector": "CEDEAR",
      "avg_return": 10.038040750743535,
      "count": 21
    },
    {
      "sector": "ETF",
      "avg_return": 7.627054154097439,
      "count": 10
    },
    {
      "sector": "Real Estate",
      "avg_return": 5.739445629777862,
      "count": 2
    },
    {
      "sector": "Financials",
      "avg_return": 5.629027952142837,
      "count": 9
    },
    {
      "sector": "Automotive",
      "avg_return": 4.858035144581829,
      "count": 3
    },
    {
      "sector": "Crypto",
      "avg_return": 4.175144809661276,
      "count": 11
    },
    {
      "sector": "Industrials",
      "avg_return": 4.071307621059458,
      "count": 6
    },
    {
      "sector": "Consumer Staples",
      "avg_return": 1.7454622436391658,
      "count": 6
    },
    {
      "sector": "Healthcare",
      "avg_return": 1.4291614599427405,
      "count": 8
    },
    {
      "sector": "Commodity",
      "avg_return": 0.7767536501089256,
      "count": 5
    },
    {
      "sector": "Utilities",
      "avg_return": 0.7551148556606102,
      "count": 2
    },
    {
      "sector": "Consumer Discretionary",
      "avg_return": -1.3504360884788285,
      "count": 5
    },
    {
      "sector": "Energy",
      "avg_return": -5.515611270610939,
      "count": 5
    },
    {
      "sector": "Communication Services",
      "avg_return": -7.035026686489457,
      "count": 4
    }
  ],
  "top_by_sector": {
    "Technology": [
      {
        "symbol": "INTC",
        "return": 91.52502741300341,
        "type": "Unknown"
      },
      {
        "symbol": "AMD",
        "return": 58.880206012786694,
        "type": "Unknown"
      },
      {
        "symbol": "MU",
        "return": 49.268888826459815,
        "type": "Unknown"
      }
    ],
    "Automotive": [
      {
        "symbol": "F",
        "return": 7.452336737609078,
        "type": "Unknown"
      },
      {
        "symbol": "GM",
        "return": 5.973150266096905,
        "type": "Unknown"
      },
      {
        "symbol": "TSLA",
        "return": 1.1486184300395053,
        "type": "Unknown"
      }
    ],
    "Financials": [
      {
        "symbol": "MS",
        "return": 15.671138201582524,
        "type": "Unknown"
      },
      {
        "symbol": "GS",
        "return": 9.52257101012215,
        "type": "Unknown"
      },
      {
        "symbol": "BAC",
        "return": 8.020512507512013,
        "type": "Unknown"
      }
    ],
    "Healthcare": [
      {
        "symbol": "UNH",
        "return": 35.544548570701615,
        "type": "Unknown"
      },
      {
        "symbol": "CVS",
        "return": 13.743777249232059,
        "type": "Unknown"
      },
      {
        "symbol": "AMGN",
        "return": -3.4901232247482317,
        "type": "Unknown"
      }
    ],
    "Energy": [
      {
        "symbol": "SLB",
        "return": 8.289554751558459,
        "type": "Unknown"
      },
      {
        "symbol": "COP",
        "return": -5.8181820493755865,
        "type": "Unknown"
      },
      {
        "symbol": "CVX",
        "return": -8.960847671850914,
        "type": "Unknown"
      }
    ],
    "Consumer Staples": [
      {
        "symbol": "PG",
        "return": 4.0523782544690246,
        "type": "Unknown"
      },
      {
        "symbol": "KO",
        "return": 3.0243199606421634,
        "type": "Unknown"
      },
      {
        "symbol": "WMT",
        "return": 2.663338904976831,
        "type": "Unknown"
      }
    ],
    "Consumer Discretionary": [
      {
        "symbol": "SBUX",
        "return": 8.583550346852608,
        "type": "Unknown"
      },
      {
        "symbol": "DIS",
        "return": 5.281182934568562,
        "type": "Unknown"
      },
      {
        "symbol": "HD",
        "return": 0.0516838160434796,
        "type": "Unknown"
      }
    ],
    "Industrials": [
      {
        "symbol": "BA",
        "return": 15.922224104792914,
        "type": "Unknown"
      },
      {
        "symbol": "CAT",
        "return": 15.663130851515694,
        "type": "Unknown"
      },
      {
        "symbol": "UPS",
        "return": 5.651560625343599,
        "type": "Unknown"
      }
    ],
    "Communication Services": [
      {
        "symbol": "NFLX",
        "return": -4.0353664287443465,
        "type": "Unknown"
      },
      {
        "symbol": "VZ",
        "return": -4.481022252002386,
        "type": "Unknown"
      },
      {
        "symbol": "T",
        "return": -9.166109215711382,
        "type": "Unknown"
      }
    ],
    "Utilities": [
      {
        "symbol": "NEE",
        "return": 3.9082741065422644,
        "type": "Unknown"
      },
      {
        "symbol": "DUK",
        "return": -2.398044395221044,
        "type": "Unknown"
      }
    ],
    "Real Estate": [
      {
        "symbol": "PLD",
        "return": 7.073692405513943,
        "type": "Unknown"
      },
      {
        "symbol": "AMT",
        "return": 4.405198854041781,
        "type": "Unknown"
      }
    ],
    "ETF": [
      {
        "symbol": "XLK",
        "return": 18.773523967551697,
        "type": "Unknown"
      },
      {
        "symbol": "QQQ",
        "return": 13.924598242672225,
        "type": "Unknown"
      },
      {
        "symbol": "EEM",
        "return": 10.917416205295872,
        "type": "Unknown"
      }
    ],
    "Commodity": [
      {
        "symbol": "USO",
        "return": 9.705309315139976,
        "type": "Unknown"
      },
      {
        "symbol": "DJP",
        "return": 2.4927311552843223,
        "type": "Unknown"
      },
      {
        "symbol": "GLD",
        "return": -1.9475248591410477,
        "type": "Unknown"
      }
    ],
    "Crypto": [
      {
        "symbol": "BTC-USD",
        "return": 11.945480259367436,
        "type": "Unknown"
      },
      {
        "symbol": "ETH-USD",
        "return": 8.83741054427707,
        "type": "Unknown"
      },
      {
        "symbol": "DOGE-USD",
        "return": 7.908210344775202,
        "type": "Unknown"
      }
    ],
    "CEDEAR": [
      {
        "symbol": "MU.BA",
        "return": 52.898185483870975,
        "type": "Unknown"
      },
      {
        "symbol": "AMZN.BA",
        "return": 26.050420168067223,
        "type": "Unknown"
      },
      {
        "symbol": "NVDA.BA",
        "return": 24.626865671641784,
        "type": "Unknown"
      }
    ]
  }
}